aq_dbmigration/__init__.py
aq_dbmigration/db_constant.py
aq_dbmigration/db_migration.py
aq_dbmigration/db_record.py
aq_dbmigration/migration_config.py
tests/__init__.py
tests/test.py
aq_dbmigration-1.0.2.dist-info/LICENSE
aq_dbmigration-1.0.2.dist-info/METADATA
aq_dbmigration-1.0.2.dist-info/WHEEL
aq_dbmigration-1.0.2.dist-info/top_level.txt
aq_dbmigration-1.0.2.dist-info/RECORD
