Metadata-Version: 2.1
Name: aq_dbmigration
Version: 1.0.2
Summary: a database migration tool
Home-page: https://github.com/nanshens/AQ-DBMigration
Author: nanshens
Author-email: 619232906@qq.com
Classifier: Programming Language :: Python :: 3
Classifier: License :: OSI Approved :: GNU General Public License v3 (GPLv3)
Classifier: Operating System :: OS Independent
Requires-Python: >=3.8
License-File: LICENSE
Requires-Dist: psycopg2 >=2.9.9
Requires-Dist: mysql-connector-python >=9.0.0
Requires-Dist: uuid >=1.30
Requires-Dist: loguru >=0.7.2
